LbEnv/Banner.py
LbEnv/Bootstrap.py
LbEnv/Info.py
LbEnv/__init__.py
LbEnv/__main__.py
LbEnv/ProjectEnv/__init__.py
LbEnv/ProjectEnv/compatibility.py
LbEnv/ProjectEnv/lookup.py
LbEnv/ProjectEnv/options.py
LbEnv/ProjectEnv/options_old.py
LbEnv/ProjectEnv/profiling.py
LbEnv/ProjectEnv/script.py
LbEnv/ProjectEnv/version.py
LbEnv/Utils/Completion.py
LbEnv/Utils/Temporary.py
LbEnv/Utils/__init__.py
LbEnv/data/aliases.csh
LbEnv/data/aliases.sh
LbEnv/data/packages.txt
LbEnv/data/projects.txt
lbenv-2.4.0.dist-info/licenses/LICENSE
lbenv-2.4.0.dist-info/METADATA
lbenv-2.4.0.dist-info/WHEEL
lbenv-2.4.0.dist-info/entry_points.txt
lbenv-2.4.0.dist-info/top_level.txt
lbenv-2.4.0.dist-info/RECORD
